[{"id": "459-0", "participant": "治疗师", "text": "来访者的孩子詹妮弗，根据你在家庭中的经历，你从中学到了什么？", "reason": ""}, {"id": "459-1", "participant": "来访者的孩子詹妮弗", "text": "我开始认识到只要我尝试独立，我就会因此觉得内疚。我的行为会激发父母的强烈反应，因为我希望能降低他们的焦虑，所以我最终决定不去寻找工作。从某个角度讲，我认为是我将他们联结在一起的。", "reason": ""}, {"id": "459-2", "participant": "治疗师", "text": "那在你看来，你在原生家庭中的行为和你在现在家庭中的行为之间有什么联系吗？", "reason": ""}, {"id": "459-3", "participant": "来访者的孩子詹妮弗", "text": "我看到我的确一直在延续这个行为模式。如果父亲暗示他对我决定从家庭中独立出去而感到不安的时候，我就会觉得我有责任去减轻他的压力。此外，我觉得我在延续我父母对待子女的方式。当我的孩子们想要从家庭中独立出去的时候，我就会使他们感到内疚。", "reason": ""}, {"id": "459-4", "participant": "治疗师", "text": "你是否还相信你的父亲不愿意让你做自己？", "reason": ""}, {"id": "459-5", "participant": "来访者", "text": "我不再那么想了。我们现在都很清楚我们其实把自己原生家庭中的行为模式带到了我们的婚姻中。我们现在的相处状况改善了很多。事实上，前阵子父亲竟然鼓励我下个学期去学校上课。", "reason": "竞然->竟然"}, {"id": "459-6", "participant": "治疗师", "text": "你的惊恐发作最近还在持续吗？", "reason": ""}, {"id": "459-7", "participant": "来访者", "text": "我还是会感到焦虑，但是现在在我知道是怎么回事之后，我已经很长一段时间没有出现惊恐发作的问题了。", "reason": "一一->在"}]